package/__init__.py
package/config_args.py
package/git_works.py
package/parse_works.py
package/vcs_p.py
package/work_args.py
tool_for_vcs-0.0.1.dist-info/METADATA
tool_for_vcs-0.0.1.dist-info/WHEEL
tool_for_vcs-0.0.1.dist-info/entry_points.txt
tool_for_vcs-0.0.1.dist-info/top_level.txt
tool_for_vcs-0.0.1.dist-info/RECORD
