Metadata-Version: 2.1
Name: tool-for-vcs
Version: 0.0.1
Summary: A demo package.
